{"loss": "tensor(1.5084)", "MAE": 1.0009354591369628, "time_this_iter_s": 0.4828047752380371, "done": false, "training_iteration": 1, "trial_id": "b04a4_00859", "date": "2023-06-30_16-37-50", "timestamp": 1688132270, "time_total_s": 0.4828047752380371, "pid": 24071, "hostname": "pe8.int.triton.aalto.fi", "node_ip": "10.10.100.8", "config": {"regression": true, "use_dnn": false, "num_epochs": 200, "batch_size": 64, "shuffle": true, "early_stopping_patience": 50, "decay_rate": 0.005, "logdir": "output", "wandb": false, "log_loss_frequency": 2, "lr": 0.03489841753715938, "l2_regularization": 4.440971373832098e-05, "output_regularization": 0.009697378702445279, "dropout": 0.0, "feature_dropout": 0.2, "num_basis_functions": 64, "hidden_sizes": [64, 32], "activation": "relu"}, "time_since_restore": 0.4828047752380371, "iterations_since_restore": 1}
{"loss": "tensor(1.3209)", "MAE": 0.94614737033844, "time_this_iter_s": 1.9001133441925049, "done": false, "training_iteration": 2, "trial_id": "b04a4_00859", "date": "2023-06-30_16-37-52", "timestamp": 1688132272, "time_total_s": 2.382918119430542, "pid": 24071, "hostname": "pe8.int.triton.aalto.fi", "node_ip": "10.10.100.8", "config": {"regression": true, "use_dnn": false, "num_epochs": 200, "batch_size": 64, "shuffle": true, "early_stopping_patience": 50, "decay_rate": 0.005, "logdir": "output", "wandb": false, "log_loss_frequency": 2, "lr": 0.03489841753715938, "l2_regularization": 4.440971373832098e-05, "output_regularization": 0.009697378702445279, "dropout": 0.0, "feature_dropout": 0.2, "num_basis_functions": 64, "hidden_sizes": [64, 32], "activation": "relu"}, "time_since_restore": 2.382918119430542, "iterations_since_restore": 2}
{"loss": "tensor(1.1821)", "MAE": 0.8966925501823425, "time_this_iter_s": 3.7070417404174805, "done": false, "training_iteration": 3, "trial_id": "b04a4_00859", "date": "2023-06-30_16-37-56", "timestamp": 1688132276, "time_total_s": 6.0899598598480225, "pid": 24071, "hostname": "pe8.int.triton.aalto.fi", "node_ip": "10.10.100.8", "config": {"regression": true, "use_dnn": false, "num_epochs": 200, "batch_size": 64, "shuffle": true, "early_stopping_patience": 50, "decay_rate": 0.005, "logdir": "output", "wandb": false, "log_loss_frequency": 2, "lr": 0.03489841753715938, "l2_regularization": 4.440971373832098e-05, "output_regularization": 0.009697378702445279, "dropout": 0.0, "feature_dropout": 0.2, "num_basis_functions": 64, "hidden_sizes": [64, 32], "activation": "relu"}, "time_since_restore": 6.0899598598480225, "iterations_since_restore": 3}
{"loss": "tensor(1.0590)", "MAE": 0.8469475507736206, "time_this_iter_s": 1.4209356307983398, "done": false, "training_iteration": 4, "trial_id": "b04a4_00859", "date": "2023-06-30_16-37-57", "timestamp": 1688132277, "time_total_s": 7.510895490646362, "pid": 24071, "hostname": "pe8.int.triton.aalto.fi", "node_ip": "10.10.100.8", "config": {"regression": true, "use_dnn": false, "num_epochs": 200, "batch_size": 64, "shuffle": true, "early_stopping_patience": 50, "decay_rate": 0.005, "logdir": "output", "wandb": false, "log_loss_frequency": 2, "lr": 0.03489841753715938, "l2_regularization": 4.440971373832098e-05, "output_regularization": 0.009697378702445279, "dropout": 0.0, "feature_dropout": 0.2, "num_basis_functions": 64, "hidden_sizes": [64, 32], "activation": "relu"}, "time_since_restore": 7.510895490646362, "iterations_since_restore": 4}
{"loss": "tensor(1.3347)", "MAE": 0.9589738249778748, "time_this_iter_s": 3.260988712310791, "done": false, "training_iteration": 5, "trial_id": "b04a4_00859", "date": "2023-06-30_16-38-00", "timestamp": 1688132280, "time_total_s": 10.771884202957153, "pid": 24071, "hostname": "pe8.int.triton.aalto.fi", "node_ip": "10.10.100.8", "config": {"regression": true, "use_dnn": false, "num_epochs": 200, "batch_size": 64, "shuffle": true, "early_stopping_patience": 50, "decay_rate": 0.005, "logdir": "output", "wandb": false, "log_loss_frequency": 2, "lr": 0.03489841753715938, "l2_regularization": 4.440971373832098e-05, "output_regularization": 0.009697378702445279, "dropout": 0.0, "feature_dropout": 0.2, "num_basis_functions": 64, "hidden_sizes": [64, 32], "activation": "relu"}, "time_since_restore": 10.771884202957153, "iterations_since_restore": 5}
{"loss": "tensor(0.8195)", "MAE": 0.7323825001716614, "time_this_iter_s": 4.415525197982788, "done": false, "training_iteration": 6, "trial_id": "b04a4_00859", "date": "2023-06-30_16-38-05", "timestamp": 1688132285, "time_total_s": 15.187409400939941, "pid": 24071, "hostname": "pe8.int.triton.aalto.fi", "node_ip": "10.10.100.8", "config": {"regression": true, "use_dnn": false, "num_epochs": 200, "batch_size": 64, "shuffle": true, "early_stopping_patience": 50, "decay_rate": 0.005, "logdir": "output", "wandb": false, "log_loss_frequency": 2, "lr": 0.03489841753715938, "l2_regularization": 4.440971373832098e-05, "output_regularization": 0.009697378702445279, "dropout": 0.0, "feature_dropout": 0.2, "num_basis_functions": 64, "hidden_sizes": [64, 32], "activation": "relu"}, "time_since_restore": 15.187409400939941, "iterations_since_restore": 6}
{"loss": "tensor(0.9743)", "MAE": 0.8158689379692078, "time_this_iter_s": 1.4441442489624023, "done": false, "training_iteration": 7, "trial_id": "b04a4_00859", "date": "2023-06-30_16-38-06", "timestamp": 1688132286, "time_total_s": 16.631553649902344, "pid": 24071, "hostname": "pe8.int.triton.aalto.fi", "node_ip": "10.10.100.8", "config": {"regression": true, "use_dnn": false, "num_epochs": 200, "batch_size": 64, "shuffle": true, "early_stopping_patience": 50, "decay_rate": 0.005, "logdir": "output", "wandb": false, "log_loss_frequency": 2, "lr": 0.03489841753715938, "l2_regularization": 4.440971373832098e-05, "output_regularization": 0.009697378702445279, "dropout": 0.0, "feature_dropout": 0.2, "num_basis_functions": 64, "hidden_sizes": [64, 32], "activation": "relu"}, "time_since_restore": 16.631553649902344, "iterations_since_restore": 7}
{"loss": "tensor(0.9287)", "MAE": 0.8016061305999755, "time_this_iter_s": 6.465435743331909, "done": false, "training_iteration": 8, "trial_id": "b04a4_00859", "date": "2023-06-30_16-38-13", "timestamp": 1688132293, "time_total_s": 23.096989393234253, "pid": 24071, "hostname": "pe8.int.triton.aalto.fi", "node_ip": "10.10.100.8", "config": {"regression": true, "use_dnn": false, "num_epochs": 200, "batch_size": 64, "shuffle": true, "early_stopping_patience": 50, "decay_rate": 0.005, "logdir": "output", "wandb": false, "log_loss_frequency": 2, "lr": 0.03489841753715938, "l2_regularization": 4.440971373832098e-05, "output_regularization": 0.009697378702445279, "dropout": 0.0, "feature_dropout": 0.2, "num_basis_functions": 64, "hidden_sizes": [64, 32], "activation": "relu"}, "time_since_restore": 23.096989393234253, "iterations_since_restore": 8}
{"loss": "tensor(0.4986)", "MAE": 0.5683989882469177, "time_this_iter_s": 2.6058263778686523, "done": false, "training_iteration": 9, "trial_id": "b04a4_00859", "date": "2023-06-30_16-38-15", "timestamp": 1688132295, "time_total_s": 25.702815771102905, "pid": 24071, "hostname": "pe8.int.triton.aalto.fi", "node_ip": "10.10.100.8", "config": {"regression": true, "use_dnn": false, "num_epochs": 200, "batch_size": 64, "shuffle": true, "early_stopping_patience": 50, "decay_rate": 0.005, "logdir": "output", "wandb": false, "log_loss_frequency": 2, "lr": 0.03489841753715938, "l2_regularization": 4.440971373832098e-05, "output_regularization": 0.009697378702445279, "dropout": 0.0, "feature_dropout": 0.2, "num_basis_functions": 64, "hidden_sizes": [64, 32], "activation": "relu"}, "time_since_restore": 25.702815771102905, "iterations_since_restore": 9}
{"loss": "tensor(0.5490)", "MAE": 0.5895718812942505, "time_this_iter_s": 6.871295690536499, "done": false, "training_iteration": 10, "trial_id": "b04a4_00859", "date": "2023-06-30_16-38-22", "timestamp": 1688132302, "time_total_s": 32.574111461639404, "pid": 24071, "hostname": "pe8.int.triton.aalto.fi", "node_ip": "10.10.100.8", "config": {"regression": true, "use_dnn": false, "num_epochs": 200, "batch_size": 64, "shuffle": true, "early_stopping_patience": 50, "decay_rate": 0.005, "logdir": "output", "wandb": false, "log_loss_frequency": 2, "lr": 0.03489841753715938, "l2_regularization": 4.440971373832098e-05, "output_regularization": 0.009697378702445279, "dropout": 0.0, "feature_dropout": 0.2, "num_basis_functions": 64, "hidden_sizes": [64, 32], "activation": "relu"}, "time_since_restore": 32.574111461639404, "iterations_since_restore": 10}
