{"loss": "tensor(1.6673)", "MAE": 1.0651776432991027, "time_this_iter_s": 2.2606396675109863, "done": false, "training_iteration": 1, "trial_id": "4467b_00662", "date": "2023-06-30_11-46-11", "timestamp": 1688114771, "time_total_s": 2.2606396675109863, "pid": 643, "hostname": "pe8.int.triton.aalto.fi", "node_ip": "10.10.100.8", "config": {"regression": true, "use_dnn": false, "num_epochs": 100, "batch_size": 64, "shuffle": true, "early_stopping_patience": 50, "decay_rate": 0.005, "logdir": "output", "wandb": false, "log_loss_frequency": 20, "lr": 0.014980658276766878, "l2_regularization": 3.50482633107767e-05, "output_regularization": 0.007650125979641792, "dropout": 0.1, "feature_dropout": 0.0, "num_basis_functions": 64, "hidden_sizes": [64, 32], "activation": "exu"}, "time_since_restore": 2.2606396675109863, "iterations_since_restore": 1}
{"loss": "tensor(1.7593)", "MAE": 1.0376542568206788, "time_this_iter_s": 3.053297281265259, "done": false, "training_iteration": 2, "trial_id": "4467b_00662", "date": "2023-06-30_11-46-14", "timestamp": 1688114774, "time_total_s": 5.313936948776245, "pid": 643, "hostname": "pe8.int.triton.aalto.fi", "node_ip": "10.10.100.8", "config": {"regression": true, "use_dnn": false, "num_epochs": 100, "batch_size": 64, "shuffle": true, "early_stopping_patience": 50, "decay_rate": 0.005, "logdir": "output", "wandb": false, "log_loss_frequency": 20, "lr": 0.014980658276766878, "l2_regularization": 3.50482633107767e-05, "output_regularization": 0.007650125979641792, "dropout": 0.1, "feature_dropout": 0.0, "num_basis_functions": 64, "hidden_sizes": [64, 32], "activation": "exu"}, "time_since_restore": 5.313936948776245, "iterations_since_restore": 2}
{"loss": "tensor(1.6199)", "MAE": 1.0070086598396302, "time_this_iter_s": 3.8878440856933594, "done": false, "training_iteration": 3, "trial_id": "4467b_00662", "date": "2023-06-30_11-46-18", "timestamp": 1688114778, "time_total_s": 9.201781034469604, "pid": 643, "hostname": "pe8.int.triton.aalto.fi", "node_ip": "10.10.100.8", "config": {"regression": true, "use_dnn": false, "num_epochs": 100, "batch_size": 64, "shuffle": true, "early_stopping_patience": 50, "decay_rate": 0.005, "logdir": "output", "wandb": false, "log_loss_frequency": 20, "lr": 0.014980658276766878, "l2_regularization": 3.50482633107767e-05, "output_regularization": 0.007650125979641792, "dropout": 0.1, "feature_dropout": 0.0, "num_basis_functions": 64, "hidden_sizes": [64, 32], "activation": "exu"}, "time_since_restore": 9.201781034469604, "iterations_since_restore": 3}
{"loss": "tensor(1.6986)", "MAE": 1.0359563946723938, "time_this_iter_s": 3.0809824466705322, "done": true, "training_iteration": 4, "trial_id": "4467b_00662", "date": "2023-06-30_11-46-21", "timestamp": 1688114781, "time_total_s": 12.282763481140137, "pid": 643, "hostname": "pe8.int.triton.aalto.fi", "node_ip": "10.10.100.8", "config": {"regression": true, "use_dnn": false, "num_epochs": 100, "batch_size": 64, "shuffle": true, "early_stopping_patience": 50, "decay_rate": 0.005, "logdir": "output", "wandb": false, "log_loss_frequency": 20, "lr": 0.014980658276766878, "l2_regularization": 3.50482633107767e-05, "output_regularization": 0.007650125979641792, "dropout": 0.1, "feature_dropout": 0.0, "num_basis_functions": 64, "hidden_sizes": [64, 32], "activation": "exu"}, "time_since_restore": 12.282763481140137, "iterations_since_restore": 4}
