{"loss": "tensor(1.4588)", "MAE": 0.9841793417930603, "time_this_iter_s": 0.232344388961792, "done": false, "training_iteration": 1, "trial_id": "b04a4_01079", "date": "2023-06-30_16-40-49", "timestamp": 1688132449, "time_total_s": 0.232344388961792, "pid": 24079, "hostname": "pe8.int.triton.aalto.fi", "node_ip": "10.10.100.8", "config": {"regression": true, "use_dnn": false, "num_epochs": 200, "batch_size": 64, "shuffle": true, "early_stopping_patience": 50, "decay_rate": 0.005, "logdir": "output", "wandb": false, "log_loss_frequency": 2, "lr": 0.0655463411169246, "l2_regularization": 3.853935219931009e-05, "output_regularization": 0.005650738783710989, "dropout": 0.0, "feature_dropout": 0.2, "num_basis_functions": 64, "hidden_sizes": [64, 32], "activation": "relu"}, "time_since_restore": 0.232344388961792, "iterations_since_restore": 1}
{"loss": "tensor(1.1628)", "MAE": 0.8845346450805665, "time_this_iter_s": 3.755711078643799, "done": false, "training_iteration": 2, "trial_id": "b04a4_01079", "date": "2023-06-30_16-40-53", "timestamp": 1688132453, "time_total_s": 3.988055467605591, "pid": 24079, "hostname": "pe8.int.triton.aalto.fi", "node_ip": "10.10.100.8", "config": {"regression": true, "use_dnn": false, "num_epochs": 200, "batch_size": 64, "shuffle": true, "early_stopping_patience": 50, "decay_rate": 0.005, "logdir": "output", "wandb": false, "log_loss_frequency": 2, "lr": 0.0655463411169246, "l2_regularization": 3.853935219931009e-05, "output_regularization": 0.005650738783710989, "dropout": 0.0, "feature_dropout": 0.2, "num_basis_functions": 64, "hidden_sizes": [64, 32], "activation": "relu"}, "time_since_restore": 3.988055467605591, "iterations_since_restore": 2}
{"loss": "tensor(1.1701)", "MAE": 0.8718046307563782, "time_this_iter_s": 1.2473931312561035, "done": false, "training_iteration": 3, "trial_id": "b04a4_01079", "date": "2023-06-30_16-40-54", "timestamp": 1688132454, "time_total_s": 5.235448598861694, "pid": 24079, "hostname": "pe8.int.triton.aalto.fi", "node_ip": "10.10.100.8", "config": {"regression": true, "use_dnn": false, "num_epochs": 200, "batch_size": 64, "shuffle": true, "early_stopping_patience": 50, "decay_rate": 0.005, "logdir": "output", "wandb": false, "log_loss_frequency": 2, "lr": 0.0655463411169246, "l2_regularization": 3.853935219931009e-05, "output_regularization": 0.005650738783710989, "dropout": 0.0, "feature_dropout": 0.2, "num_basis_functions": 64, "hidden_sizes": [64, 32], "activation": "relu"}, "time_since_restore": 5.235448598861694, "iterations_since_restore": 3}
{"loss": "tensor(0.8653)", "MAE": 0.7674110651016235, "time_this_iter_s": 5.353342533111572, "done": false, "training_iteration": 4, "trial_id": "b04a4_01079", "date": "2023-06-30_16-41-00", "timestamp": 1688132460, "time_total_s": 10.588791131973267, "pid": 24079, "hostname": "pe8.int.triton.aalto.fi", "node_ip": "10.10.100.8", "config": {"regression": true, "use_dnn": false, "num_epochs": 200, "batch_size": 64, "shuffle": true, "early_stopping_patience": 50, "decay_rate": 0.005, "logdir": "output", "wandb": false, "log_loss_frequency": 2, "lr": 0.0655463411169246, "l2_regularization": 3.853935219931009e-05, "output_regularization": 0.005650738783710989, "dropout": 0.0, "feature_dropout": 0.2, "num_basis_functions": 64, "hidden_sizes": [64, 32], "activation": "relu"}, "time_since_restore": 10.588791131973267, "iterations_since_restore": 4}
{"loss": "tensor(0.8749)", "MAE": 0.7754497766494751, "time_this_iter_s": 2.280618667602539, "done": false, "training_iteration": 5, "trial_id": "b04a4_01079", "date": "2023-06-30_16-41-02", "timestamp": 1688132462, "time_total_s": 12.869409799575806, "pid": 24079, "hostname": "pe8.int.triton.aalto.fi", "node_ip": "10.10.100.8", "config": {"regression": true, "use_dnn": false, "num_epochs": 200, "batch_size": 64, "shuffle": true, "early_stopping_patience": 50, "decay_rate": 0.005, "logdir": "output", "wandb": false, "log_loss_frequency": 2, "lr": 0.0655463411169246, "l2_regularization": 3.853935219931009e-05, "output_regularization": 0.005650738783710989, "dropout": 0.0, "feature_dropout": 0.2, "num_basis_functions": 64, "hidden_sizes": [64, 32], "activation": "relu"}, "time_since_restore": 12.869409799575806, "iterations_since_restore": 5}
{"loss": "tensor(0.9419)", "MAE": 0.7980106234550476, "time_this_iter_s": 0.5037486553192139, "done": false, "training_iteration": 6, "trial_id": "b04a4_01079", "date": "2023-06-30_16-41-03", "timestamp": 1688132463, "time_total_s": 13.37315845489502, "pid": 24079, "hostname": "pe8.int.triton.aalto.fi", "node_ip": "10.10.100.8", "config": {"regression": true, "use_dnn": false, "num_epochs": 200, "batch_size": 64, "shuffle": true, "early_stopping_patience": 50, "decay_rate": 0.005, "logdir": "output", "wandb": false, "log_loss_frequency": 2, "lr": 0.0655463411169246, "l2_regularization": 3.853935219931009e-05, "output_regularization": 0.005650738783710989, "dropout": 0.0, "feature_dropout": 0.2, "num_basis_functions": 64, "hidden_sizes": [64, 32], "activation": "relu"}, "time_since_restore": 13.37315845489502, "iterations_since_restore": 6}
{"loss": "tensor(0.5898)", "MAE": 0.5792510747909546, "time_this_iter_s": 0.39717864990234375, "done": false, "training_iteration": 7, "trial_id": "b04a4_01079", "date": "2023-06-30_16-41-03", "timestamp": 1688132463, "time_total_s": 13.770337104797363, "pid": 24079, "hostname": "pe8.int.triton.aalto.fi", "node_ip": "10.10.100.8", "config": {"regression": true, "use_dnn": false, "num_epochs": 200, "batch_size": 64, "shuffle": true, "early_stopping_patience": 50, "decay_rate": 0.005, "logdir": "output", "wandb": false, "log_loss_frequency": 2, "lr": 0.0655463411169246, "l2_regularization": 3.853935219931009e-05, "output_regularization": 0.005650738783710989, "dropout": 0.0, "feature_dropout": 0.2, "num_basis_functions": 64, "hidden_sizes": [64, 32], "activation": "relu"}, "time_since_restore": 13.770337104797363, "iterations_since_restore": 7}
{"loss": "tensor(0.8282)", "MAE": 0.752963387966156, "time_this_iter_s": 0.5836617946624756, "done": false, "training_iteration": 8, "trial_id": "b04a4_01079", "date": "2023-06-30_16-41-04", "timestamp": 1688132464, "time_total_s": 14.353998899459839, "pid": 24079, "hostname": "pe8.int.triton.aalto.fi", "node_ip": "10.10.100.8", "config": {"regression": true, "use_dnn": false, "num_epochs": 200, "batch_size": 64, "shuffle": true, "early_stopping_patience": 50, "decay_rate": 0.005, "logdir": "output", "wandb": false, "log_loss_frequency": 2, "lr": 0.0655463411169246, "l2_regularization": 3.853935219931009e-05, "output_regularization": 0.005650738783710989, "dropout": 0.0, "feature_dropout": 0.2, "num_basis_functions": 64, "hidden_sizes": [64, 32], "activation": "relu"}, "time_since_restore": 14.353998899459839, "iterations_since_restore": 8}
{"loss": "tensor(0.5077)", "MAE": 0.572607445716858, "time_this_iter_s": 0.2084648609161377, "done": false, "training_iteration": 9, "trial_id": "b04a4_01079", "date": "2023-06-30_16-41-04", "timestamp": 1688132464, "time_total_s": 14.562463760375977, "pid": 24079, "hostname": "pe8.int.triton.aalto.fi", "node_ip": "10.10.100.8", "config": {"regression": true, "use_dnn": false, "num_epochs": 200, "batch_size": 64, "shuffle": true, "early_stopping_patience": 50, "decay_rate": 0.005, "logdir": "output", "wandb": false, "log_loss_frequency": 2, "lr": 0.0655463411169246, "l2_regularization": 3.853935219931009e-05, "output_regularization": 0.005650738783710989, "dropout": 0.0, "feature_dropout": 0.2, "num_basis_functions": 64, "hidden_sizes": [64, 32], "activation": "relu"}, "time_since_restore": 14.562463760375977, "iterations_since_restore": 9}
{"loss": "tensor(0.5326)", "MAE": 0.5780352354049683, "time_this_iter_s": 0.2191009521484375, "done": false, "training_iteration": 10, "trial_id": "b04a4_01079", "date": "2023-06-30_16-41-04", "timestamp": 1688132464, "time_total_s": 14.781564712524414, "pid": 24079, "hostname": "pe8.int.triton.aalto.fi", "node_ip": "10.10.100.8", "config": {"regression": true, "use_dnn": false, "num_epochs": 200, "batch_size": 64, "shuffle": true, "early_stopping_patience": 50, "decay_rate": 0.005, "logdir": "output", "wandb": false, "log_loss_frequency": 2, "lr": 0.0655463411169246, "l2_regularization": 3.853935219931009e-05, "output_regularization": 0.005650738783710989, "dropout": 0.0, "feature_dropout": 0.2, "num_basis_functions": 64, "hidden_sizes": [64, 32], "activation": "relu"}, "time_since_restore": 14.781564712524414, "iterations_since_restore": 10}
