{"loss": "tensor(1.7028)", "MAE": 0.9886125087738037, "time_this_iter_s": 3.2192635536193848, "done": false, "training_iteration": 1, "trial_id": "4467b_00046", "date": "2023-06-30_11-32-01", "timestamp": 1688113921, "time_total_s": 3.2192635536193848, "pid": 641, "hostname": "pe8.int.triton.aalto.fi", "node_ip": "10.10.100.8", "config": {"regression": true, "use_dnn": false, "num_epochs": 100, "batch_size": 64, "shuffle": true, "early_stopping_patience": 50, "decay_rate": 0.005, "logdir": "output", "wandb": false, "log_loss_frequency": 20, "lr": 0.06772276037548093, "l2_regularization": 1.988347913891895e-06, "output_regularization": 0.030704731658902355, "dropout": 0.1, "feature_dropout": 0.1, "num_basis_functions": 64, "hidden_sizes": [64, 32], "activation": "exu"}, "time_since_restore": 3.2192635536193848, "iterations_since_restore": 1}
{"loss": "tensor(1.6347)", "MAE": 1.0176692008972168, "time_this_iter_s": 3.365098476409912, "done": false, "training_iteration": 2, "trial_id": "4467b_00046", "date": "2023-06-30_11-32-04", "timestamp": 1688113924, "time_total_s": 6.584362030029297, "pid": 641, "hostname": "pe8.int.triton.aalto.fi", "node_ip": "10.10.100.8", "config": {"regression": true, "use_dnn": false, "num_epochs": 100, "batch_size": 64, "shuffle": true, "early_stopping_patience": 50, "decay_rate": 0.005, "logdir": "output", "wandb": false, "log_loss_frequency": 20, "lr": 0.06772276037548093, "l2_regularization": 1.988347913891895e-06, "output_regularization": 0.030704731658902355, "dropout": 0.1, "feature_dropout": 0.1, "num_basis_functions": 64, "hidden_sizes": [64, 32], "activation": "exu"}, "time_since_restore": 6.584362030029297, "iterations_since_restore": 2}
{"loss": "tensor(1.6404)", "MAE": 1.0277000188827514, "time_this_iter_s": 3.1268928050994873, "done": false, "training_iteration": 3, "trial_id": "4467b_00046", "date": "2023-06-30_11-32-07", "timestamp": 1688113927, "time_total_s": 9.711254835128784, "pid": 641, "hostname": "pe8.int.triton.aalto.fi", "node_ip": "10.10.100.8", "config": {"regression": true, "use_dnn": false, "num_epochs": 100, "batch_size": 64, "shuffle": true, "early_stopping_patience": 50, "decay_rate": 0.005, "logdir": "output", "wandb": false, "log_loss_frequency": 20, "lr": 0.06772276037548093, "l2_regularization": 1.988347913891895e-06, "output_regularization": 0.030704731658902355, "dropout": 0.1, "feature_dropout": 0.1, "num_basis_functions": 64, "hidden_sizes": [64, 32], "activation": "exu"}, "time_since_restore": 9.711254835128784, "iterations_since_restore": 3}
{"loss": "tensor(1.4484)", "MAE": 0.9732998490333558, "time_this_iter_s": 3.3799643516540527, "done": true, "training_iteration": 4, "trial_id": "4467b_00046", "date": "2023-06-30_11-32-11", "timestamp": 1688113931, "time_total_s": 13.091219186782837, "pid": 641, "hostname": "pe8.int.triton.aalto.fi", "node_ip": "10.10.100.8", "config": {"regression": true, "use_dnn": false, "num_epochs": 100, "batch_size": 64, "shuffle": true, "early_stopping_patience": 50, "decay_rate": 0.005, "logdir": "output", "wandb": false, "log_loss_frequency": 20, "lr": 0.06772276037548093, "l2_regularization": 1.988347913891895e-06, "output_regularization": 0.030704731658902355, "dropout": 0.1, "feature_dropout": 0.1, "num_basis_functions": 64, "hidden_sizes": [64, 32], "activation": "exu"}, "time_since_restore": 13.091219186782837, "iterations_since_restore": 4}
