{"loss": "tensor(1.9252)", "MAE": 1.099720287322998, "time_this_iter_s": 3.261127471923828, "done": false, "training_iteration": 1, "trial_id": "4467b_00774", "date": "2023-06-30_11-49-40", "timestamp": 1688114980, "time_total_s": 3.261127471923828, "pid": 641, "hostname": "pe8.int.triton.aalto.fi", "node_ip": "10.10.100.8", "config": {"regression": true, "use_dnn": false, "num_epochs": 100, "batch_size": 64, "shuffle": true, "early_stopping_patience": 50, "decay_rate": 0.005, "logdir": "output", "wandb": false, "log_loss_frequency": 20, "lr": 0.002068366185032308, "l2_regularization": 1.0288704223621268e-05, "output_regularization": 0.0029291404854585317, "dropout": 0.2, "feature_dropout": 0.0, "num_basis_functions": 64, "hidden_sizes": [64, 32], "activation": "exu"}, "time_since_restore": 3.261127471923828, "iterations_since_restore": 1}
{"loss": "tensor(1.7032)", "MAE": 1.052820885181427, "time_this_iter_s": 1.613506555557251, "done": false, "training_iteration": 2, "trial_id": "4467b_00774", "date": "2023-06-30_11-49-41", "timestamp": 1688114981, "time_total_s": 4.874634027481079, "pid": 641, "hostname": "pe8.int.triton.aalto.fi", "node_ip": "10.10.100.8", "config": {"regression": true, "use_dnn": false, "num_epochs": 100, "batch_size": 64, "shuffle": true, "early_stopping_patience": 50, "decay_rate": 0.005, "logdir": "output", "wandb": false, "log_loss_frequency": 20, "lr": 0.002068366185032308, "l2_regularization": 1.0288704223621268e-05, "output_regularization": 0.0029291404854585317, "dropout": 0.2, "feature_dropout": 0.0, "num_basis_functions": 64, "hidden_sizes": [64, 32], "activation": "exu"}, "time_since_restore": 4.874634027481079, "iterations_since_restore": 2}
{"loss": "tensor(2.1386)", "MAE": 1.1497501850128173, "time_this_iter_s": 4.622228384017944, "done": false, "training_iteration": 3, "trial_id": "4467b_00774", "date": "2023-06-30_11-49-46", "timestamp": 1688114986, "time_total_s": 9.496862411499023, "pid": 641, "hostname": "pe8.int.triton.aalto.fi", "node_ip": "10.10.100.8", "config": {"regression": true, "use_dnn": false, "num_epochs": 100, "batch_size": 64, "shuffle": true, "early_stopping_patience": 50, "decay_rate": 0.005, "logdir": "output", "wandb": false, "log_loss_frequency": 20, "lr": 0.002068366185032308, "l2_regularization": 1.0288704223621268e-05, "output_regularization": 0.0029291404854585317, "dropout": 0.2, "feature_dropout": 0.0, "num_basis_functions": 64, "hidden_sizes": [64, 32], "activation": "exu"}, "time_since_restore": 9.496862411499023, "iterations_since_restore": 3}
{"loss": "tensor(1.9723)", "MAE": 1.1121861457824707, "time_this_iter_s": 3.0861904621124268, "done": true, "training_iteration": 4, "trial_id": "4467b_00774", "date": "2023-06-30_11-49-49", "timestamp": 1688114989, "time_total_s": 12.58305287361145, "pid": 641, "hostname": "pe8.int.triton.aalto.fi", "node_ip": "10.10.100.8", "config": {"regression": true, "use_dnn": false, "num_epochs": 100, "batch_size": 64, "shuffle": true, "early_stopping_patience": 50, "decay_rate": 0.005, "logdir": "output", "wandb": false, "log_loss_frequency": 20, "lr": 0.002068366185032308, "l2_regularization": 1.0288704223621268e-05, "output_regularization": 0.0029291404854585317, "dropout": 0.2, "feature_dropout": 0.0, "num_basis_functions": 64, "hidden_sizes": [64, 32], "activation": "exu"}, "time_since_restore": 12.58305287361145, "iterations_since_restore": 4}
