{"loss": "tensor(1.5189)", "MAE": 0.9986060261726379, "time_this_iter_s": 3.104412317276001, "done": false, "training_iteration": 1, "trial_id": "b04a4_00113", "date": "2023-06-30_16-29-13", "timestamp": 1688131753, "time_total_s": 3.104412317276001, "pid": 24079, "hostname": "pe8.int.triton.aalto.fi", "node_ip": "10.10.100.8", "config": {"regression": true, "use_dnn": false, "num_epochs": 200, "batch_size": 64, "shuffle": true, "early_stopping_patience": 50, "decay_rate": 0.005, "logdir": "output", "wandb": false, "log_loss_frequency": 2, "lr": 0.03165685166188096, "l2_regularization": 2.894566005182172e-06, "output_regularization": 0.024082828864350626, "dropout": 0.1, "feature_dropout": 0.0, "num_basis_functions": 64, "hidden_sizes": [64, 32], "activation": "relu"}, "time_since_restore": 3.104412317276001, "iterations_since_restore": 1}
{"loss": "tensor(1.3234)", "MAE": 0.9353737711906434, "time_this_iter_s": 3.2269225120544434, "done": false, "training_iteration": 2, "trial_id": "b04a4_00113", "date": "2023-06-30_16-29-16", "timestamp": 1688131756, "time_total_s": 6.331334829330444, "pid": 24079, "hostname": "pe8.int.triton.aalto.fi", "node_ip": "10.10.100.8", "config": {"regression": true, "use_dnn": false, "num_epochs": 200, "batch_size": 64, "shuffle": true, "early_stopping_patience": 50, "decay_rate": 0.005, "logdir": "output", "wandb": false, "log_loss_frequency": 2, "lr": 0.03165685166188096, "l2_regularization": 2.894566005182172e-06, "output_regularization": 0.024082828864350626, "dropout": 0.1, "feature_dropout": 0.0, "num_basis_functions": 64, "hidden_sizes": [64, 32], "activation": "relu"}, "time_since_restore": 6.331334829330444, "iterations_since_restore": 2}
{"loss": "tensor(0.9461)", "MAE": 0.78448566198349, "time_this_iter_s": 3.1786935329437256, "done": false, "training_iteration": 3, "trial_id": "b04a4_00113", "date": "2023-06-30_16-29-20", "timestamp": 1688131760, "time_total_s": 9.51002836227417, "pid": 24079, "hostname": "pe8.int.triton.aalto.fi", "node_ip": "10.10.100.8", "config": {"regression": true, "use_dnn": false, "num_epochs": 200, "batch_size": 64, "shuffle": true, "early_stopping_patience": 50, "decay_rate": 0.005, "logdir": "output", "wandb": false, "log_loss_frequency": 2, "lr": 0.03165685166188096, "l2_regularization": 2.894566005182172e-06, "output_regularization": 0.024082828864350626, "dropout": 0.1, "feature_dropout": 0.0, "num_basis_functions": 64, "hidden_sizes": [64, 32], "activation": "relu"}, "time_since_restore": 9.51002836227417, "iterations_since_restore": 3}
{"loss": "tensor(1.2969)", "MAE": 0.931249737739563, "time_this_iter_s": 3.4930849075317383, "done": true, "training_iteration": 4, "trial_id": "b04a4_00113", "date": "2023-06-30_16-29-23", "timestamp": 1688131763, "time_total_s": 13.003113269805908, "pid": 24079, "hostname": "pe8.int.triton.aalto.fi", "node_ip": "10.10.100.8", "config": {"regression": true, "use_dnn": false, "num_epochs": 200, "batch_size": 64, "shuffle": true, "early_stopping_patience": 50, "decay_rate": 0.005, "logdir": "output", "wandb": false, "log_loss_frequency": 2, "lr": 0.03165685166188096, "l2_regularization": 2.894566005182172e-06, "output_regularization": 0.024082828864350626, "dropout": 0.1, "feature_dropout": 0.0, "num_basis_functions": 64, "hidden_sizes": [64, 32], "activation": "relu"}, "time_since_restore": 13.003113269805908, "iterations_since_restore": 4}
