{"loss": "tensor(3.2865)", "MAE": 1.4466947078704835, "time_this_iter_s": 5.985692739486694, "done": true, "training_iteration": 1, "trial_id": "c8e1a_00010", "date": "2023-06-30_11-13-55", "timestamp": 1688112835, "time_total_s": 5.985692739486694, "pid": 16667, "hostname": "pe8.int.triton.aalto.fi", "node_ip": "10.10.100.8", "config": {"regression": true, "use_dnn": false, "num_epochs": 10, "batch_size": 32, "shuffle": true, "early_stopping_patience": 50, "decay_rate": 0.005, "logdir": "output", "wandb": false, "log_loss_frequency": 20, "lr": 0.06591987786315445, "l2_regularization": 5.167022250059006e-06, "output_regularization": 0.04960037739402104, "dropout": 0.5, "feature_dropout": 0.0, "num_basis_functions": 64, "hidden_sizes": [64, 32], "activation": "exu"}, "time_since_restore": 5.985692739486694, "iterations_since_restore": 1}
