{"loss": "tensor(3.0762)", "MAE": 1.415444564819336, "time_this_iter_s": 2.5303781032562256, "done": true, "training_iteration": 1, "trial_id": "b04a4_00779", "date": "2023-06-30_16-36-48", "timestamp": 1688132208, "time_total_s": 2.5303781032562256, "pid": 24079, "hostname": "pe8.int.triton.aalto.fi", "node_ip": "10.10.100.8", "config": {"regression": true, "use_dnn": false, "num_epochs": 200, "batch_size": 64, "shuffle": true, "early_stopping_patience": 50, "decay_rate": 0.005, "logdir": "output", "wandb": false, "log_loss_frequency": 2, "lr": 0.001092388332534735, "l2_regularization": 3.111039893012503e-05, "output_regularization": 0.003230433362889564, "dropout": 0.4, "feature_dropout": 0.0, "num_basis_functions": 64, "hidden_sizes": [64, 32], "activation": "relu"}, "time_since_restore": 2.5303781032562256, "iterations_since_restore": 1}
