{"loss": "tensor(4.3382)", "MAE": 1.7030658721923828, "time_this_iter_s": 3.2374706268310547, "done": true, "training_iteration": 1, "trial_id": "4467b_00077", "date": "2023-06-30_11-32-34", "timestamp": 1688113954, "time_total_s": 3.2374706268310547, "pid": 638, "hostname": "pe8.int.triton.aalto.fi", "node_ip": "10.10.100.8", "config": {"regression": true, "use_dnn": false, "num_epochs": 100, "batch_size": 64, "shuffle": true, "early_stopping_patience": 50, "decay_rate": 0.005, "logdir": "output", "wandb": false, "log_loss_frequency": 20, "lr": 0.002615774417717081, "l2_regularization": 1.014637516755115e-05, "output_regularization": 0.0012578490702077154, "dropout": 0.5, "feature_dropout": 0.15000000000000002, "num_basis_functions": 64, "hidden_sizes": [64, 32], "activation": "relu"}, "time_since_restore": 3.2374706268310547, "iterations_since_restore": 1}
