{"loss": "tensor(17.6489)", "MAE": 3.979583740234375, "time_this_iter_s": 3.215085744857788, "done": true, "training_iteration": 1, "trial_id": "b04a4_00082", "date": "2023-06-30_16-28-57", "timestamp": 1688131737, "time_total_s": 3.215085744857788, "pid": 24078, "hostname": "pe8.int.triton.aalto.fi", "node_ip": "10.10.100.8", "config": {"regression": true, "use_dnn": false, "num_epochs": 200, "batch_size": 64, "shuffle": true, "early_stopping_patience": 50, "decay_rate": 0.005, "logdir": "output", "wandb": false, "log_loss_frequency": 2, "lr": 0.001493107240462993, "l2_regularization": 2.489227976936632e-06, "output_regularization": 0.0021492083655586746, "dropout": 0.8, "feature_dropout": 0.15000000000000002, "num_basis_functions": 64, "hidden_sizes": [64, 32], "activation": "exu"}, "time_since_restore": 3.215085744857788, "iterations_since_restore": 1}
