{"loss": "tensor(5.0013)", "MAE": 1.8672629475593567, "time_this_iter_s": 6.177868127822876, "done": true, "training_iteration": 1, "trial_id": "c8e1a_00054", "date": "2023-06-30_11-14-49", "timestamp": 1688112889, "time_total_s": 6.177868127822876, "pid": 16665, "hostname": "pe8.int.triton.aalto.fi", "node_ip": "10.10.100.8", "config": {"regression": true, "use_dnn": false, "num_epochs": 10, "batch_size": 32, "shuffle": true, "early_stopping_patience": 50, "decay_rate": 0.005, "logdir": "output", "wandb": false, "log_loss_frequency": 20, "lr": 0.0031206261110182454, "l2_regularization": 9.443465476474695e-05, "output_regularization": 0.014593790421226802, "dropout": 0.5, "feature_dropout": 0.1, "num_basis_functions": 64, "hidden_sizes": [64, 32], "activation": "exu"}, "time_since_restore": 6.177868127822876, "iterations_since_restore": 1}
