{
    "os": "Linux-3.10.0-1160.88.1.el7.x86_64-x86_64-with-glibc2.17",
    "python": "3.10.8",
    "heartbeatAt": "2023-07-04T18:14:34.321985",
    "startedAt": "2023-07-04T18:14:33.759674",
    "docker": null,
    "cuda": null,
    "args": null,
    "state": "running",
    "program": "<python with no main file>",
    "git": {
        "remote": "https://github.com/D2phus/reproduced-nam.git",
        "commit": "bfa267cdf2ff17ac14eba52a16ca7066b87a07a7"
    },
    "email": "xinyuzhang_cs@outlook.com",
    "root": "/scratch/work/zhangx18/reproduced-nam",
    "host": "pe5.int.triton.aalto.fi",
    "username": "zhangx18",
    "executable": "/share/apps/anaconda-ci/fgci-centos7-anaconda/software/anaconda/2023-02/d63245c4/bin/python",
    "cpu_count": 24,
    "cpu_count_logical": 24,
    "cpu_freq": {
        "current": 2923.9967916666665,
        "min": 1200.0,
        "max": 3300.0
    },
    "cpu_freq_per_core": [
        {
            "current": 3136.901,
            "min": 1200.0,
            "max": 3300.0
        },
        {
            "current": 3099.975,
            "min": 1200.0,
            "max": 3300.0
        },
        {
            "current": 2908.782,
            "min": 1200.0,
            "max": 3300.0
        },
        {
            "current": 2900.543,
            "min": 1200.0,
            "max": 3300.0
        },
        {
            "current": 2957.916,
            "min": 1200.0,
            "max": 3300.0
        },
        {
            "current": 2936.096,
            "min": 1200.0,
            "max": 3300.0
        },
        {
            "current": 3111.419,
            "min": 1200.0,
            "max": 3300.0
        },
        {
            "current": 3028.869,
            "min": 1200.0,
            "max": 3300.0
        },
        {
            "current": 2902.984,
            "min": 1200.0,
            "max": 3300.0
        },
        {
            "current": 3033.905,
            "min": 1200.0,
            "max": 3300.0
        },
        {
            "current": 3060.302,
            "min": 1200.0,
            "max": 3300.0
        },
        {
            "current": 2908.477,
            "min": 1200.0,
            "max": 3300.0
        },
        {
            "current": 2978.363,
            "min": 1200.0,
            "max": 3300.0
        },
        {
            "current": 3099.975,
            "min": 1200.0,
            "max": 3300.0
        },
        {
            "current": 3053.894,
            "min": 1200.0,
            "max": 3300.0
        },
        {
            "current": 2899.932,
            "min": 1200.0,
            "max": 3300.0
        },
        {
            "current": 2891.082,
            "min": 1200.0,
            "max": 3300.0
        },
        {
            "current": 2627.563,
            "min": 1200.0,
            "max": 3300.0
        },
        {
            "current": 2830.505,
            "min": 1200.0,
            "max": 3300.0
        },
        {
            "current": 2580.261,
            "min": 1200.0,
            "max": 3300.0
        },
        {
            "current": 2813.568,
            "min": 1200.0,
            "max": 3300.0
        },
        {
            "current": 2899.932,
            "min": 1200.0,
            "max": 3300.0
        },
        {
            "current": 2862.091,
            "min": 1200.0,
            "max": 3300.0
        },
        {
            "current": 2689.819,
            "min": 1200.0,
            "max": 3300.0
        }
    ],
    "disk": {
        "total": 13.331954956054688,
        "used": 5.627635955810547
    },
    "memory": {
        "total": 125.8253402709961
    }
}
