{
    "os": "Linux-3.10.0-1160.88.1.el7.x86_64-x86_64-with-glibc2.17",
    "python": "3.10.8",
    "heartbeatAt": "2023-07-04T12:53:11.875504",
    "startedAt": "2023-07-04T12:53:11.364797",
    "docker": null,
    "cuda": null,
    "args": null,
    "state": "running",
    "program": "<python with no main file>",
    "git": {
        "remote": "https://github.com/D2phus/reproduced-nam.git",
        "commit": "bfa267cdf2ff17ac14eba52a16ca7066b87a07a7"
    },
    "email": "xinyuzhang_cs@outlook.com",
    "root": "/scratch/work/zhangx18/reproduced-nam",
    "host": "pe8.int.triton.aalto.fi",
    "username": "zhangx18",
    "executable": "/share/apps/anaconda-ci/fgci-centos7-anaconda/software/anaconda/2023-02/d63245c4/bin/python",
    "cpu_count": 24,
    "cpu_count_logical": 24,
    "cpu_freq": {
        "current": 2549.17725,
        "min": 1200.0,
        "max": 3300.0
    },
    "cpu_freq_per_core": [
        {
            "current": 1499.938,
            "min": 1200.0,
            "max": 3300.0
        },
        {
            "current": 1470.184,
            "min": 1200.0,
            "max": 3300.0
        },
        {
            "current": 2950.744,
            "min": 1200.0,
            "max": 3300.0
        },
        {
            "current": 1454.467,
            "min": 1200.0,
            "max": 3300.0
        },
        {
            "current": 3177.185,
            "min": 1200.0,
            "max": 3300.0
        },
        {
            "current": 2973.785,
            "min": 1200.0,
            "max": 3300.0
        },
        {
            "current": 2531.738,
            "min": 1200.0,
            "max": 3300.0
        },
        {
            "current": 2384.643,
            "min": 1200.0,
            "max": 3300.0
        },
        {
            "current": 2896.881,
            "min": 1200.0,
            "max": 3300.0
        },
        {
            "current": 1564.178,
            "min": 1200.0,
            "max": 3300.0
        },
        {
            "current": 2854.919,
            "min": 1200.0,
            "max": 3300.0
        },
        {
            "current": 2935.485,
            "min": 1200.0,
            "max": 3300.0
        },
        {
            "current": 3061.523,
            "min": 1200.0,
            "max": 3300.0
        },
        {
            "current": 2198.181,
            "min": 1200.0,
            "max": 3300.0
        },
        {
            "current": 3065.795,
            "min": 1200.0,
            "max": 3300.0
        },
        {
            "current": 2848.51,
            "min": 1200.0,
            "max": 3300.0
        },
        {
            "current": 2959.136,
            "min": 1200.0,
            "max": 3300.0
        },
        {
            "current": 2624.664,
            "min": 1200.0,
            "max": 3300.0
        },
        {
            "current": 2899.932,
            "min": 1200.0,
            "max": 3300.0
        },
        {
            "current": 1771.697,
            "min": 1200.0,
            "max": 3300.0
        },
        {
            "current": 3300.323,
            "min": 1200.0,
            "max": 3300.0
        },
        {
            "current": 1887.969,
            "min": 1200.0,
            "max": 3300.0
        },
        {
            "current": 2982.177,
            "min": 1200.0,
            "max": 3300.0
        },
        {
            "current": 1263.58,
            "min": 1200.0,
            "max": 3300.0
        }
    ],
    "disk": {
        "total": 13.331954956054688,
        "used": 5.4850311279296875
    },
    "memory": {
        "total": 125.8253402709961
    }
}
