{"loss": "tensor(1.6968)", "MAE": 1.0366065740585326, "time_this_iter_s": 3.3099894523620605, "done": false, "training_iteration": 1, "trial_id": "4467b_00024", "date": "2023-06-30_11-31-42", "timestamp": 1688113902, "time_total_s": 3.3099894523620605, "pid": 640, "hostname": "pe8.int.triton.aalto.fi", "node_ip": "10.10.100.8", "config": {"regression": true, "use_dnn": false, "num_epochs": 100, "batch_size": 64, "shuffle": true, "early_stopping_patience": 50, "decay_rate": 0.005, "logdir": "output", "wandb": false, "log_loss_frequency": 20, "lr": 0.010583239291859933, "l2_regularization": 2.673409540975077e-05, "output_regularization": 0.00987036938974167, "dropout": 0.1, "feature_dropout": 0.05, "num_basis_functions": 64, "hidden_sizes": [64, 32], "activation": "exu"}, "time_since_restore": 3.3099894523620605, "iterations_since_restore": 1}
{"loss": "tensor(1.3825)", "MAE": 0.9510323524475097, "time_this_iter_s": 3.3885459899902344, "done": false, "training_iteration": 2, "trial_id": "4467b_00024", "date": "2023-06-30_11-31-46", "timestamp": 1688113906, "time_total_s": 6.698535442352295, "pid": 640, "hostname": "pe8.int.triton.aalto.fi", "node_ip": "10.10.100.8", "config": {"regression": true, "use_dnn": false, "num_epochs": 100, "batch_size": 64, "shuffle": true, "early_stopping_patience": 50, "decay_rate": 0.005, "logdir": "output", "wandb": false, "log_loss_frequency": 20, "lr": 0.010583239291859933, "l2_regularization": 2.673409540975077e-05, "output_regularization": 0.00987036938974167, "dropout": 0.1, "feature_dropout": 0.05, "num_basis_functions": 64, "hidden_sizes": [64, 32], "activation": "exu"}, "time_since_restore": 6.698535442352295, "iterations_since_restore": 2}
{"loss": "tensor(1.4623)", "MAE": 0.9723708510398865, "time_this_iter_s": 3.3292086124420166, "done": false, "training_iteration": 3, "trial_id": "4467b_00024", "date": "2023-06-30_11-31-49", "timestamp": 1688113909, "time_total_s": 10.027744054794312, "pid": 640, "hostname": "pe8.int.triton.aalto.fi", "node_ip": "10.10.100.8", "config": {"regression": true, "use_dnn": false, "num_epochs": 100, "batch_size": 64, "shuffle": true, "early_stopping_patience": 50, "decay_rate": 0.005, "logdir": "output", "wandb": false, "log_loss_frequency": 20, "lr": 0.010583239291859933, "l2_regularization": 2.673409540975077e-05, "output_regularization": 0.00987036938974167, "dropout": 0.1, "feature_dropout": 0.05, "num_basis_functions": 64, "hidden_sizes": [64, 32], "activation": "exu"}, "time_since_restore": 10.027744054794312, "iterations_since_restore": 3}
{"loss": "tensor(1.7356)", "MAE": 1.039398741722107, "time_this_iter_s": 3.2978670597076416, "done": true, "training_iteration": 4, "trial_id": "4467b_00024", "date": "2023-06-30_11-31-52", "timestamp": 1688113912, "time_total_s": 13.325611114501953, "pid": 640, "hostname": "pe8.int.triton.aalto.fi", "node_ip": "10.10.100.8", "config": {"regression": true, "use_dnn": false, "num_epochs": 100, "batch_size": 64, "shuffle": true, "early_stopping_patience": 50, "decay_rate": 0.005, "logdir": "output", "wandb": false, "log_loss_frequency": 20, "lr": 0.010583239291859933, "l2_regularization": 2.673409540975077e-05, "output_regularization": 0.00987036938974167, "dropout": 0.1, "feature_dropout": 0.05, "num_basis_functions": 64, "hidden_sizes": [64, 32], "activation": "exu"}, "time_since_restore": 13.325611114501953, "iterations_since_restore": 4}
