{
    "os": "Linux-3.10.0-1160.88.1.el7.x86_64-x86_64-with-glibc2.17",
    "python": "3.10.8",
    "heartbeatAt": "2023-07-03T09:36:54.650365",
    "startedAt": "2023-07-03T09:36:54.069316",
    "docker": null,
    "cuda": null,
    "args": null,
    "state": "running",
    "program": "<python with no main file>",
    "git": {
        "remote": "https://github.com/D2phus/reproduced-nam.git",
        "commit": "8970e2732322e0e44eb9211f3a8edcacf345d840"
    },
    "email": "xinyuzhang_cs@outlook.com",
    "root": "/scratch/work/zhangx18/reproduced-nam",
    "host": "pe5.int.triton.aalto.fi",
    "username": "zhangx18",
    "executable": "/share/apps/anaconda-ci/fgci-centos7-anaconda/software/anaconda/2023-02/d63245c4/bin/python",
    "cpu_count": 24,
    "cpu_count_logical": 24,
    "cpu_freq": {
        "current": 2745.030208333333,
        "min": 1200.0,
        "max": 3300.0
    },
    "cpu_freq_per_core": [
        {
            "current": 3252.258,
            "min": 1200.0,
            "max": 3300.0
        },
        {
            "current": 2938.385,
            "min": 1200.0,
            "max": 3300.0
        },
        {
            "current": 3116.912,
            "min": 1200.0,
            "max": 3300.0
        },
        {
            "current": 3021.697,
            "min": 1200.0,
            "max": 3300.0
        },
        {
            "current": 1887.054,
            "min": 1200.0,
            "max": 3300.0
        },
        {
            "current": 3004.455,
            "min": 1200.0,
            "max": 3300.0
        },
        {
            "current": 3154.754,
            "min": 1200.0,
            "max": 3300.0
        },
        {
            "current": 2821.96,
            "min": 1200.0,
            "max": 3300.0
        },
        {
            "current": 2537.536,
            "min": 1200.0,
            "max": 3300.0
        },
        {
            "current": 2900.085,
            "min": 1200.0,
            "max": 3300.0
        },
        {
            "current": 3106.689,
            "min": 1200.0,
            "max": 3300.0
        },
        {
            "current": 2900.238,
            "min": 1200.0,
            "max": 3300.0
        },
        {
            "current": 2941.741,
            "min": 1200.0,
            "max": 3300.0
        },
        {
            "current": 2639.007,
            "min": 1200.0,
            "max": 3300.0
        },
        {
            "current": 2919.464,
            "min": 1200.0,
            "max": 3300.0
        },
        {
            "current": 3034.82,
            "min": 1200.0,
            "max": 3300.0
        },
        {
            "current": 2628.784,
            "min": 1200.0,
            "max": 3300.0
        },
        {
            "current": 2889.709,
            "min": 1200.0,
            "max": 3300.0
        },
        {
            "current": 2897.033,
            "min": 1200.0,
            "max": 3300.0
        },
        {
            "current": 2900.238,
            "min": 1200.0,
            "max": 3300.0
        },
        {
            "current": 1200.103,
            "min": 1200.0,
            "max": 3300.0
        },
        {
            "current": 2864.685,
            "min": 1200.0,
            "max": 3300.0
        },
        {
            "current": 1518.096,
            "min": 1200.0,
            "max": 3300.0
        },
        {
            "current": 2899.932,
            "min": 1200.0,
            "max": 3300.0
        }
    ],
    "disk": {
        "total": 13.331954956054688,
        "used": 5.603496551513672
    },
    "memory": {
        "total": 125.8253402709961
    }
}
