{"loss": "tensor(11.9582)", "MAE": 3.196104955673218, "time_this_iter_s": 2.523375988006592, "done": true, "training_iteration": 1, "trial_id": "4467b_00806", "date": "2023-06-30_11-50-13", "timestamp": 1688115013, "time_total_s": 2.523375988006592, "pid": 640, "hostname": "pe8.int.triton.aalto.fi", "node_ip": "10.10.100.8", "config": {"regression": true, "use_dnn": false, "num_epochs": 100, "batch_size": 64, "shuffle": true, "early_stopping_patience": 50, "decay_rate": 0.005, "logdir": "output", "wandb": false, "log_loss_frequency": 20, "lr": 0.01565850909085951, "l2_regularization": 1.943745612346909e-06, "output_regularization": 0.003368284778758603, "dropout": 0.7000000000000001, "feature_dropout": 0.05, "num_basis_functions": 64, "hidden_sizes": [64, 32], "activation": "exu"}, "time_since_restore": 2.523375988006592, "iterations_since_restore": 1}
